odoo/addons/stock_dynamic_routing_checkout_sync/README.rst
odoo/addons/stock_dynamic_routing_checkout_sync/__init__.py
odoo/addons/stock_dynamic_routing_checkout_sync/__manifest__.py
odoo/addons/stock_dynamic_routing_checkout_sync/i18n/es_AR.po
odoo/addons/stock_dynamic_routing_checkout_sync/i18n/it.po
odoo/addons/stock_dynamic_routing_checkout_sync/i18n/pt_BR.po
odoo/addons/stock_dynamic_routing_checkout_sync/i18n/stock_dynamic_routing_checkout_sync.pot
odoo/addons/stock_dynamic_routing_checkout_sync/models/__init__.py
odoo/addons/stock_dynamic_routing_checkout_sync/readme/CONTRIBUTORS.rst
odoo/addons/stock_dynamic_routing_checkout_sync/readme/CREDITS.rst
odoo/addons/stock_dynamic_routing_checkout_sync/readme/DESCRIPTION.rst
odoo/addons/stock_dynamic_routing_checkout_sync/static/description/icon.png
odoo/addons/stock_dynamic_routing_checkout_sync/static/description/index.html
odoo/addons/stock_dynamic_routing_checkout_sync/tests/__init__.py
odoo/addons/stock_dynamic_routing_checkout_sync/tests/test_routing_sync.py
odoo14_addon_stock_dynamic_routing_checkout_sync-14.0.1.0.1.dev7.dist-info/METADATA
odoo14_addon_stock_dynamic_routing_checkout_sync-14.0.1.0.1.dev7.dist-info/WHEEL
odoo14_addon_stock_dynamic_routing_checkout_sync-14.0.1.0.1.dev7.dist-info/top_level.txt
odoo14_addon_stock_dynamic_routing_checkout_sync-14.0.1.0.1.dev7.dist-info/RECORD
