Metadata-Version: 2.1
Name: odoo14-addon-stock-dynamic-routing-checkout-sync
Version: 14.0.1.0.1.dev7
Summary: Glue module for tests when dynamic routing and checkout sync are used
Home-page: https://github.com/OCA/wms
Author: Camptocamp, Odoo Community Association (OCA)
Author-email: support@odoo-community.org
License: AGPL-3
Platform: UNKNOWN
Classifier: Programming Language :: Python
Classifier: Framework :: Odoo
Classifier: Framework :: Odoo :: 14.0
Classifier: License :: OSI Approved :: GNU Affero General Public License v3
Classifier: Development Status :: 3 - Alpha
Requires-Python: >=3.6
Requires-Dist: odoo14-addon-stock-checkout-sync
Requires-Dist: odoo14-addon-stock-dynamic-routing
Requires-Dist: odoo <14.1dev,>=14.0a
